pyoncat/LICENSE
pyoncat/__init__.py
pyoncat/reduction.py
pyoncat-2.4.dist-info/METADATA
pyoncat-2.4.dist-info/WHEEL
pyoncat-2.4.dist-info/RECORD
