Metadata-Version: 2.4
Name: pyoncat
Version: 2.4
Summary: A Python Client for ONCat (the ORNL Neutron Catalog).
Keywords: ornl,neutron,metadata,catalog
Author: ONCat Support
Author-email: oncat-support@ornl.gov
Requires-Python: >=3.7,<4
Classifier: Programming Language :: Python :: 3
Classifier: Programming Language :: Python :: 3.7
Classifier: Programming Language :: Python :: 3.8
Classifier: Programming Language :: Python :: 3.9
Classifier: Programming Language :: Python :: 3.10
Classifier: Programming Language :: Python :: 3.11
Classifier: Programming Language :: Python :: 3.12
Classifier: Programming Language :: Python :: 3.13
Classifier: Programming Language :: Python :: 3.14
Requires-Dist: requests
Project-URL: Homepage, https://oncat.ornl.gov
